integrationos/__init__.py
integrationos/client.py
integrationos/paginate.py
integrationos/resource.py
integrationos/utils.py
integrationos/types/__init__.py
integrationos/types/generic.py
integrationos/types/models.py
integrationos-0.1.3.dist-info/METADATA
integrationos-0.1.3.dist-info/WHEEL
integrationos-0.1.3.dist-info/top_level.txt
integrationos-0.1.3.dist-info/RECORD
