Metadata-Version: 2.1
Name: integrationos
Version: 0.1.3
Summary: A Python SDK for IntegrationOS
Requires-Python: >=3.7
Requires-Dist: httpx
Requires-Dist: pydantic
Requires-Dist: python-dotenv
Requires-Dist: case-converter
Requires-Dist: jinja2
Requires-Dist: requests
Requires-Dist: email-validator
Provides-Extra: test
Requires-Dist: pytest<8.0.0,>=7.0.0; extra == "test"
